LICENSE
adacord/__init__.py
adacord/cli/__init__.py
adacord/cli/api.py
adacord/cli/api_tokens.py
adacord/cli/auth.py
adacord/cli/bucket.py
adacord/cli/commons.py
adacord/cli/exceptions.py
adacord/cli/main.py
adacord-0.1.13.dist-info/entry_points.txt
adacord-0.1.13.dist-info/LICENSE
adacord-0.1.13.dist-info/WHEEL
adacord-0.1.13.dist-info/METADATA
adacord-0.1.13.dist-info/RECORD
